fastapi_auth_sqlalchemy_models/__init__.py
fastapi_auth_sqlalchemy_models/models.py
fastapi_auth_sqlalchemy_models/repositories.py
fastapi_auth_sqlalchemy_models-0.0.6.dist-info/METADATA
fastapi_auth_sqlalchemy_models-0.0.6.dist-info/WHEEL
fastapi_auth_sqlalchemy_models-0.0.6.dist-info/licenses/LICENSE
fastapi_auth_sqlalchemy_models-0.0.6.dist-info/RECORD
